git_publish/__init__.py
git_publish/git_project.py
git_publish/github_project.py
git_publish/gitlab_project.py
git_publish/main.py
git_publish-0.1.0.dist-info/METADATA
git_publish-0.1.0.dist-info/WHEEL
git_publish-0.1.0.dist-info/entry_points.txt
git_publish-0.1.0.dist-info/licenses/LICENSE
git_publish-0.1.0.dist-info/RECORD
