Metadata-Version: 2.4
Name: git-publish
Version: 0.1.0
Summary: A stack diff poor-man's solution
Project-URL: Homepage, https://github.com/warrenseine/git-publish
Project-URL: Repository, https://github.com/warrenseine/git-publish
Project-URL: Issues, https://github.com/warrenseine/git-publish/issues
Project-URL: Changelog, https://github.com/warrenseine/git-publish/releases
Author-email: Warren Seine <warren.seine@gmail.com>
License: MIT
License-File: LICENSE
Keywords: git,merge requests,publish,pull requests,stacked
Classifier: Environment :: Console
Classifier: Intended Audience :: Developers
Classifier: License :: OSI Approved :: MIT License
Classifier: Operating System :: OS Independent
Classifier: Programming Language :: Python :: 3
Classifier: Programming Language :: Python :: 3 :: Only
Classifier: Programming Language :: Python :: 3.10
Classifier: Programming Language :: Python :: 3.11
Classifier: Programming Language :: Python :: 3.12
Classifier: Topic :: Software Development :: Version Control :: Git
Requires-Python: >=3.10
Requires-Dist: gitpython<4,>=3.1.41
Requires-Dist: giturlparse<1,>=0.12.0
Requires-Dist: pygithub<3,>2.1.1
Requires-Dist: python-dotenv<2,>=1.0.0
Requires-Dist: python-gitlab<6,>=5.6.0
